CHANGELOG.txt
LICENSE.txt
MANIFEST.in
README.txt
setup.py
cellsaga.egg-info/PKG-INFO
cellsaga.egg-info/SOURCES.txt
cellsaga.egg-info/dependency_links.txt
cellsaga.egg-info/requires.txt
cellsaga.egg-info/top_level.txt
immopro/__init__.py