Metadata-Version: 1.1
Name: cellsaga
Version: 0.0.2
Summary: Cell Saga Module
Home-page: UNKNOWN
Author: Abhinav Thakur
Author-email: abhinav237.thakur@gmail.com
License: MIT
Keywords: cell
Platform: UNKNOWN
Classifier: Development Status :: 5 - Production/Stable
Classifier: Intended Audience :: Education
Classifier: Operating System :: Microsoft :: Windows :: Windows 10
Classifier: License :: OSI Approved :: MIT License
Classifier: Programming Language :: Python :: 3
